AUTHORS
LICENSE
MANIFEST.in
README.md
pyproject.toml
setup.py
csrc/cugae/gae.cu
csrc/custom_all_reduce/custom_all_reduce.cu
csrc/custom_all_reduce/custom_all_reduce.cuh
csrc/custom_all_reduce/custom_all_reduce_test.cu
csrc/custom_all_reduce/pybind.cpp
csrc/interval_op/interval_op.cpp
csrc/interval_op/interval_op.cu
csrc/search/device_mesh.cpp
csrc/search/device_mesh.hpp
csrc/search/rpc.cpp
csrc/search/rpc.hpp
csrc/search/search.cpp
csrc/search/simulate.cpp
csrc/search/simulate.hpp
docs/source/conf.py
examples/load_and_eval_rw.py
examples/visualize_dfg.py
examples/customized_exp/ppo_ref_ema.py
examples/customized_exp/ppo_sentiment.py
examples/new_algorithms/grpo/grpo_exp.py
examples/new_algorithms/grpo/grpo_interface.py
examples/new_algorithms/reinforce/reinforce_exp.py
examples/new_algorithms/reinforce/reinforce_interface.py
realhf/__init__.py
realhf.egg-info/PKG-INFO
realhf.egg-info/SOURCES.txt
realhf.egg-info/dependency_links.txt
realhf.egg-info/top_level.txt
realhf/api/core/config.py
realhf/api/core/data_api.py
realhf/api/core/dfg.py
realhf/api/core/model_api.py
realhf/api/core/system_api.py
realhf/api/from_hf/__init__.py
realhf/api/from_hf/gemma.py
realhf/api/from_hf/gpt2.py
realhf/api/from_hf/llama.py
realhf/api/from_hf/mistral.py
realhf/api/from_hf/mixtral.py
realhf/api/from_hf/qwen2.py
realhf/api/quickstart/__init__.py
realhf/api/quickstart/dataset.py
realhf/api/quickstart/device_mesh.py
realhf/api/quickstart/entrypoint.py
realhf/api/quickstart/model.py
realhf/api/quickstart/search.py
realhf/apps/__init__.py
realhf/apps/main.py
realhf/apps/profile_layers.py
realhf/apps/quickstart.py
realhf/apps/remote.py
realhf/base/__init__.py
realhf/base/asyncio_utils.py
realhf/base/cluster.py
realhf/base/constants.py
realhf/base/datapack.py
realhf/base/gpu_utils.py
realhf/base/importing.py
realhf/base/logging.py
realhf/base/monitor.py
realhf/base/name_resolve.py
realhf/base/names.py
realhf/base/network.py
realhf/base/numpy_utils.py
realhf/base/ray_utils.py
realhf/base/recover.py
realhf/base/saveload_utils.py
realhf/base/security.py
realhf/base/seeding.py
realhf/base/slurm_utils.py
