Metadata-Version: 2.1
Name: realhf
Version: 0.3.0
Summary: ReaL: Efficient RLHF Training of Large Language Models with Parameter Reallocation
Author-email: Zhiyu Mei <meizy20@mails.tsinghua.edu.cn>, Wei Fu <fuwth17@gmail.com>
Maintainer-email: Zhiyu Mei <meizy20@mails.tsinghua.edu.cn>, Wei Fu <fuwth17@gmail.com>
Project-URL: Homepage, https://github.com/openpsi-project/ReaLHF
Project-URL: Issues, https://github.com/openpsi-project/ReaLHF/issues
Project-URL: Documentation, https://openpsi-project.github.io/ReaLHF/
Project-URL: Repository, https://github.com/openpsi-project/ReaLHF
Keywords: distributed-systems,reinforcement-learning-from-human-feedback,large-language-models,llm-training
Classifier: Development Status :: 2 - Pre-Alpha
Classifier: Environment :: GPU :: NVIDIA CUDA :: 12 :: 12.2
Classifier: Intended Audience :: Developers
Classifier: Programming Language :: Python :: 3
Classifier: Programming Language :: Python :: 3.10
Requires-Python: <3.12,>=3.10
License-File: LICENSE
License-File: AUTHORS
